{
    "configurations": [
        {
            "name": "Win32",
            "includePath": [
                "${workspaceFolder}/**",
                "C:/Users/bibi/Downloads/glfw-3.3.7/glfw-3.3.7/deps",
                "C:/Users/bibi/Downloads/glfw-3.3.7/glfw-3.3.7/include"
            ],
            "defines": [
                "_DEBUG",
                "UNICODE",
                "_UNICODE"
            ],
            "compilerPath": "C:\\Program Files\\mingw-w64\\x86_64-8.1.0-win32-sjlj-rt_v6-rev0\\mingw64\\bin\\gcc.exe",
            "intelliSenseMode": "windows-gcc-x64"
        }
    ],
    "version": 4
}